sprechstimme/__init__.py
sprechstimme/core.py
sprechstimme/filters.py
sprechstimme/playback.py
sprechstimme/track.py
sprechstimme/waves.py
sprechstimme-1.8.10.dist-info/licenses/AUTHORS
sprechstimme-1.8.10.dist-info/licenses/LICENSE
sprechstimme-1.8.10.dist-info/METADATA
sprechstimme-1.8.10.dist-info/WHEEL
sprechstimme-1.8.10.dist-info/top_level.txt
sprechstimme-1.8.10.dist-info/RECORD
