Metadata-Version: 2.4
Name: sprechstimme
Version: 1.8.10
Summary: A modular Python synthesizer and sequencer
Author: liquidsound
License: Apache-2.0
Project-URL: Homepage, https://github.com/breatn/sprechstimme
Requires-Python: >=3.8
License-File: LICENSE
License-File: AUTHORS
Requires-Dist: numpy
Requires-Dist: sounddevice
Requires-Dist: scipy
Dynamic: license-file
